lighthouse/__init__.py
lighthouse/_client/attributes.py
lighthouse/_client/client.py
lighthouse/_client/constants.py
lighthouse/_client/datasets.py
lighthouse/_client/environment_variables.py
lighthouse/_client/get_client.py
lighthouse/_client/ingest_exporter.py
lighthouse/_client/observe.py
lighthouse/_client/resource_manager.py
lighthouse/_client/span.py
lighthouse/_client/span_processor.py
lighthouse/_client/utils.py
lighthouse/_task_manager/media_manager.py
lighthouse/_task_manager/media_upload_consumer.py
lighthouse/_task_manager/media_upload_queue.py
lighthouse/_task_manager/score_ingestion_consumer.py
lighthouse/_utils/__init__.py
lighthouse/_utils/environment.py
lighthouse/_utils/error_logging.py
lighthouse/_utils/parse_error.py
lighthouse/_utils/prompt_cache.py
lighthouse/_utils/request.py
lighthouse/_utils/serializer.py
lighthouse/api/README.md
lighthouse/api/__init__.py
lighthouse/api/client.py
lighthouse/api/core/__init__.py
lighthouse/api/core/api_error.py
lighthouse/api/core/client_wrapper.py
lighthouse/api/core/datetime_utils.py
lighthouse/api/core/file.py
lighthouse/api/core/http_client.py
lighthouse/api/core/jsonable_encoder.py
lighthouse/api/core/pydantic_utilities.py
lighthouse/api/core/query_encoder.py
lighthouse/api/core/remove_none_from_dict.py
lighthouse/api/core/request_options.py
lighthouse/api/reference.md
lighthouse/api/resources/__init__.py
lighthouse/api/resources/annotation_queues/__init__.py
lighthouse/api/resources/annotation_queues/client.py
lighthouse/api/resources/annotation_queues/types/__init__.py
lighthouse/api/resources/annotation_queues/types/annotation_queue.py
lighthouse/api/resources/annotation_queues/types/annotation_queue_item.py
lighthouse/api/resources/annotation_queues/types/annotation_queue_object_type.py
lighthouse/api/resources/annotation_queues/types/annotation_queue_status.py
lighthouse/api/resources/annotation_queues/types/create_annotation_queue_item_request.py
lighthouse_observability_sdk-3.2.4.dist-info/LICENSE
lighthouse_observability_sdk-3.2.4.dist-info/METADATA
lighthouse_observability_sdk-3.2.4.dist-info/WHEEL
lighthouse_observability_sdk-3.2.4.dist-info/entry_points.txt
lighthouse_observability_sdk-3.2.4.dist-info/RECORD
